lamya/__init__.py
lamya/__main__.py
lamya/config.py
lamya/content_processing.py
lamya/content_tree.py
lamya/site_generator.py
lamya/themes/lamya/static/css/main.css
lamya/themes/lamya/static/css/normalize.css
lamya/themes/lamya/static/css/pygments.css
lamya/themes/lamya/static/img/caret-down.svg
lamya/themes/lamya/static/img/menu-2.svg
lamya/themes/lamya/static/img/moon.svg
lamya/themes/lamya/static/img/sun.svg
lamya/themes/lamya/static/js/nav_aria.js
lamya/themes/lamya/templates/404.html
lamya/themes/lamya/templates/base.html
lamya/themes/lamya/templates/default.html
lamya/themes/lamya/templates/header.html
lamya/themes/lamya/templates/sidebar.html
lamya-1.0.6.dist-info/LICENSE
lamya-1.0.6.dist-info/METADATA
lamya-1.0.6.dist-info/WHEEL
lamya-1.0.6.dist-info/top_level.txt
lamya-1.0.6.dist-info/RECORD
