Metadata-Version: 2.1
Name: lamya
Version: 1.0.6
Summary: The lamyà package provides both an out of the box markdown static site generator and a framework for building your own custom ones.
Author-email: Vasil Shotarov <vshotarov@gmail.com>
Project-URL: Homepage, https://github.com/vshotarov/lamya
Project-URL: Bug Tracker, https://github.com/vshotarov/lamya/issues
Project-URL: Documentation, https://lamya.readthedocs.io/en/latest/index.html
Classifier: Programming Language :: Python :: 3
Classifier: License :: OSI Approved :: GNU General Public License v3 (GPLv3)
Classifier: Operating System :: OS Independent
Requires-Python: >=3.8
License-File: LICENSE
Provides-Extra: all
Requires-Dist: Markdown (==3.3.3) ; extra == 'all'
Requires-Dist: Jinja2 (>=3) ; extra == 'all'
